rendseq/__init__.py
rendseq/file_funcs.py
rendseq/make_peaks.py
rendseq/ramps_steps.py
rendseq/utility_funcs.py
rendseq/zscores.py
rendseq-0.1.9.dist-info/LICENSE
rendseq-0.1.9.dist-info/METADATA
rendseq-0.1.9.dist-info/WHEEL
rendseq-0.1.9.dist-info/top_level.txt
rendseq-0.1.9.dist-info/RECORD
