Metadata-Version: 2.1
Name: rendseq
Version: 0.1.9
Summary: Package for RendSeq Data Analysis
Home-page: https://github.com/miraep8/rendseq
Author: Mirae Parker
Author-email: rendseq@mit.edu
License: MIT
Requires-Python: >=3.6
License-File: LICENSE
